odoo/addons/company_country/README.rst
odoo/addons/company_country/__init__.py
odoo/addons/company_country/__manifest__.py
odoo/addons/company_country/i18n/company_country.pot
odoo/addons/company_country/migrations/13.0.1.0.2/pre-migration.py
odoo/addons/company_country/readme/CONFIGURE.rst
odoo/addons/company_country/readme/CONTRIBUTORS.rst
odoo/addons/company_country/readme/CREDITS.rst
odoo/addons/company_country/readme/DESCRIPTION.rst
odoo/addons/company_country/readme/INSTALL.rst
odoo/addons/company_country/readme/USAGE.rst
odoo/addons/company_country/static/description/icon.png
odoo/addons/company_country/static/description/index.html
odoo13_addon_company_country-13.0.2.0.1.dist-info/METADATA
odoo13_addon_company_country-13.0.2.0.1.dist-info/WHEEL
odoo13_addon_company_country-13.0.2.0.1.dist-info/top_level.txt
odoo13_addon_company_country-13.0.2.0.1.dist-info/RECORD
